ekf_slam_3d/__init__.py
ekf_slam_3d/data_classes/__init__.py
ekf_slam_3d/data_classes/lie_algebra.py
ekf_slam_3d/data_classes/map.py
ekf_slam_3d/data_classes/sensors.py
ekf_slam_3d/data_classes/slam.py
ekf_slam_3d/data_classes/state_history.py
ekf_slam_3d/modules/__init__.py
ekf_slam_3d/modules/controller.py
ekf_slam_3d/modules/kalman.py
ekf_slam_3d/modules/kalman_extended.py
ekf_slam_3d/modules/math_utils.py
ekf_slam_3d/modules/simulators.py
ekf_slam_3d/modules/state_space.py
ekf_slam_3d-0.1.0.dist-info/LICENSE
ekf_slam_3d-0.1.0.dist-info/METADATA
ekf_slam_3d-0.1.0.dist-info/WHEEL
ekf_slam_3d-0.1.0.dist-info/RECORD
